fmatch/__init__.py
fmatch/logrus.py
fmatch/matcher.py
fmatch/test_fmatch.py
fmatch/tests/__init__.py
fmatch/tests/test_matcher.py
fmatch-0.1.6.dist-info/licenses/LICENSE
fmatch-0.1.6.dist-info/METADATA
fmatch-0.1.6.dist-info/WHEEL
fmatch-0.1.6.dist-info/top_level.txt
fmatch-0.1.6.dist-info/RECORD
