Metadata-Version: 2.4
Name: fmatch
Version: 0.1.6
Summary: Common package for matching runs with provided metadata
Author: sboyapal
Author-email: sboyapal@redhat.com
Keywords: python,matching,red hat,perf-scale,matcher,orion
Classifier: Development Status :: 1 - Planning
Classifier: Intended Audience :: Developers
Classifier: Programming Language :: Python :: 3
Classifier: Operating System :: Unix
Classifier: Operating System :: MacOS :: MacOS X
Classifier: Operating System :: Microsoft :: Windows
License-File: LICENSE
Requires-Dist: elasticsearch==7.13.0
Requires-Dist: elasticsearch-dsl
Requires-Dist: pyyaml
Requires-Dist: pandas
Dynamic: author
Dynamic: author-email
Dynamic: classifier
Dynamic: description
Dynamic: description-content-type
Dynamic: keywords
Dynamic: license-file
Dynamic: requires-dist
Dynamic: summary
